meshcatmods/__init__.py
meshcatmods/animation.py
meshcatmods/commands.py
meshcatmods/geometry.py
meshcatmods/path.py
meshcatmods/transformations.py
meshcatmods/visualizer.py
meshcatmods/servers/__init__.py
meshcatmods/servers/tree.py
meshcatmods/servers/zmqserver.py
meshcatmods/tests/__init__.py
meshcatmods/tests/dummy_websocket_client.py
meshcatmods/tests/test_drawing.py
meshcatmods/tests/test_ports.py
meshcatmods/tests/test_start_server.py
meshcatmods/tests/data/mesh_0_convex_piece_0.dae
meshcatmods/tests/data/mesh_0_convex_piece_0.obj
meshcatmods/tests/data/mesh_0_convex_piece_0.stl_ascii
meshcatmods/tests/data/mesh_0_convex_piece_0.stl_binary
meshcatmods/viewer/LICENSE
meshcatmods/viewer/Readme.md
meshcatmods/viewer/package.json
meshcatmods/viewer/webpack.config.js
meshcatmods/viewer/yarn.lock
meshcatmods/viewer/data/HeadTextureMultisense.png
meshcatmods/viewer/data/head_multisense.obj
meshcatmods/viewer/src/index.js
meshcatmods/viewer/test/animation.html
meshcatmods/viewer/test/background.html
meshcatmods/viewer/test/camera_control.html
meshcatmods/viewer/test/empty_scene.html
meshcatmods/viewer/test/meshfile_geometry_dae.html
meshcatmods/viewer/test/meshfile_geometry_obj.html
meshcatmods/viewer/test/meshfile_geometry_stl.html
meshcatmods/viewer/test/meshfile_object_dae.html
meshcatmods/viewer/test/meshfile_object_obj.html
meshcatmods/viewer/test/orthographic_camera.html
meshcatmods-0.1.2.dist-info/LICENSE.txt
meshcatmods-0.1.2.dist-info/METADATA
meshcatmods-0.1.2.dist-info/WHEEL
meshcatmods-0.1.2.dist-info/entry_points.txt
meshcatmods-0.1.2.dist-info/top_level.txt
meshcatmods-0.1.2.dist-info/RECORD
